<?xml version="1.0" encoding="UTF-8"?>
<scene>
    <!-- Scene Information -->
    <scene_name>wok scene</scene_name>
	<light_position>
		<x>0.0</x>
		<y>4.5</y>
		<z>2.0</z>
	</light_position>
	<plane_texture_location>../assets/textures/Stylized_Wood_basecolor.tga</plane_texture_location>
    <skydome_location>../assets/industrial_sunset_puresky_4k.hdr</skydome_location>

    <!-- Object List -->
    <objects>
        <!-- Object 1 -->
        <object>
            <mesh_idx>0</mesh_idx>
            <material_idx>0</material_idx>
            <position>
                <x>0.0</x>
                <y>1</y>
                <z>2.8</z>
            </position>
            <rotation>
                <x>-90.0</x>
                <y>0.0</y>
                <z>180.0</z>
            </rotation>
			<scale>
                <x>0.005</x>
                <y>0.005</y>
                <z>0.005</z>
            </scale>
        </object>

        <!-- Add more objects as needed -->
    </objects>
	<!-- Mesh List -->
    <meshes>
        <!-- Mesh 0 -->
        <mesh>
			<id>0</id>
            <model_location>../assets/urna.obj</model_location>
			<scale>
                <x>0.005</x>
                <y>0.005</y>
                <z>0.005</z>
            </scale>
        </mesh>

        <!-- Add more objects as needed -->
    </meshes>
	<materials>
		<!-- Material 0 -->
		<material>
			<id>0</id>
			<reflectivity>0.0</reflectivity>
			<refractivity>0.0</refractivity>
			<absorption>
                <x>0.0</x>
                <y>0.0</y>
                <z>0.0</z>
            </absorption>
			<texture_location>../assets/textures/urna.jpg</texture_location>
		</material>
	</materials>
</scene>
